calculator/__init__.py
calculator/calculator.py
Easy_Calculator_By_Sanbil-0.0.1.dist-info/LICENSE.txt
Easy_Calculator_By_Sanbil-0.0.1.dist-info/METADATA
Easy_Calculator_By_Sanbil-0.0.1.dist-info/WHEEL
Easy_Calculator_By_Sanbil-0.0.1.dist-info/top_level.txt
Easy_Calculator_By_Sanbil-0.0.1.dist-info/RECORD
